README
setup.py
pboost/__init__.py
pboost/plot.py
pboost/run.py
pboost.egg-info/PKG-INFO
pboost.egg-info/SOURCES.txt
pboost.egg-info/dependency_links.txt
pboost.egg-info/not-zip-safe
pboost.egg-info/requires.txt
pboost.egg-info/top_level.txt
pboost/boost/__init__.py
pboost/boost/adaboost.py
pboost/boost/adaboost_fast.py
pboost/boost/confidence_rated.py
pboost/boost/decision_tree.py
pboost/boost/generic.py
pboost/boost/process.py
pboost/boost/rankboost.py
pboost/environment/__init__.py
pboost/environment/pb.py
pboost/feature/__init__.py
pboost/feature/extract.py
pboost/feature/factory.py
pboost/pblite/__init__.py
pboost/pblite/pb.py
pboost/report/__init__.py
pboost/report/final_classifier_script.py
pboost/report/pyroc.py
pboost/report/reporter.py
pboost/utility/__init__.py
pboost/utility/checkFile.py
pboost/utility/parser.py