Metadata-Version: 1.1
Name: pboost
Version: 0.5.4
Summary: Parallel Implementation of Boosting Algorithms with MPI.
Home-page: https://github.com/mbasbug/pboost
Author: Mehmet Basbug
Author-email: mbasbug@princeton.edu
License: UNKNOWN
Platform: UNKNOWN
Classifier: Development Status :: 4 - Beta
Classifier: Environment :: Console
Classifier: Framework :: Buildout
Classifier: Intended Audience :: Information Technology
Classifier: License :: Free for non-commercial use
Classifier: Natural Language :: English
Classifier: Operating System :: OS Independent
Classifier: Programming Language :: Python
Classifier: Topic :: Scientific/Engineering :: Artificial Intelligence
